newsfeed/__init__.py
newsfeed/admin.py
newsfeed/app_settings.py
newsfeed/apps.py
newsfeed/constants.py
newsfeed/forms.py
newsfeed/models.py
newsfeed/querysets.py
newsfeed/signals.py
newsfeed/urls.py
newsfeed/views.py
newsfeed/migrations/0001_initial.py
newsfeed/migrations/0002_alter_issue_issue_type.py
newsfeed/migrations/__init__.py
newsfeed/static/newsfeed/js/newsletter_subscription.js
newsfeed/templates/newsfeed/base.html
newsfeed/templates/newsfeed/issue_detail.html
newsfeed/templates/newsfeed/issue_list.html
newsfeed/templates/newsfeed/issue_posts.html
newsfeed/templates/newsfeed/latest_issue.html
newsfeed/templates/newsfeed/messages.html
newsfeed/templates/newsfeed/newsletter_subscribe.html
newsfeed/templates/newsfeed/newsletter_subscription_confirm.html
newsfeed/templates/newsfeed/newsletter_unsubscribe.html
newsfeed/templates/newsfeed/subscription_form.html
newsfeed/templates/newsfeed/email/email_verification.html
newsfeed/templates/newsfeed/email/email_verification.txt
newsfeed/templates/newsfeed/email/email_verification_subject.txt
newsfeed/templates/newsfeed/email/newsletter_email.html
newsfeed/utils/__init__.py
newsfeed/utils/check_ajax.py
newsfeed/utils/send_newsletters.py
newsfeed/utils/send_verification.py
django_newsfeed-0.8.8.dist-info/LICENSE
django_newsfeed-0.8.8.dist-info/METADATA
django_newsfeed-0.8.8.dist-info/WHEEL
django_newsfeed-0.8.8.dist-info/top_level.txt
django_newsfeed-0.8.8.dist-info/RECORD
