Metadata-Version: 2.1
Name: django-newsfeed
Version: 0.8.8
Summary: A news curator and newsletter subscription package for django
Home-page: https://github.com/saadmk11/django-newsfeed
Author: Maksudul Haque
Author-email: saad.mk112@gmail.com
License: GNU Public License
Keywords: django-newsfeed news curator newsletter subscription
Classifier: Development Status :: 4 - Beta
Classifier: Framework :: Django
Classifier: Intended Audience :: Developers
Classifier: License :: OSI Approved :: GNU General Public License v3 (GPLv3)
Classifier: Natural Language :: English
Classifier: Operating System :: OS Independent
Classifier: Programming Language :: Python :: 3.6
Classifier: Programming Language :: Python :: 3.7
Classifier: Programming Language :: Python :: 3.8
Classifier: Programming Language :: Python :: 3.9
Classifier: Programming Language :: Python :: 3.10
Classifier: Framework :: Django
Classifier: Framework :: Django :: 2.2
Classifier: Framework :: Django :: 3.0
Classifier: Framework :: Django :: 3.1
Classifier: Framework :: Django :: 3.2
Classifier: Framework :: Django :: 4.0
Requires-Python: >=3.6
License-File: LICENSE
Requires-Dist: Django (>=2.2)
